isolationforest/IsolationForest.py
isolationforest/__init__.py
IsolationForest-1.1.0.dist-info/METADATA
IsolationForest-1.1.0.dist-info/WHEEL
IsolationForest-1.1.0.dist-info/top_level.txt
IsolationForest-1.1.0.dist-info/RECORD
