Metadata-Version: 2.1
Name: IsolationForest
Version: 1.1.0
Summary: An implementation of the Isolation Forest anomaly detection algorithm.
Home-page: https://github.com/msimms/LibIsolationForest
Author: Mike Simms
Author-email: mike@mikesimms.net
License: MIT
Platform: UNKNOWN
Classifier: Programming Language :: Python :: 2
Classifier: License :: OSI Approved :: MIT License
Classifier: Operating System :: OS Independent
Requires-Python: ==2.7.*
